{"tests/test_app.py::TestApp::test_get_app": {"type": "brittle", "detected_sequence": [["tests/test_app.py::TestApp::test_update_app_validation", "tests/test_app.py::TestApp::test_add_ssl", "tests/test_app.py::TestApp::test_create_app", "tests/test_app.py::TestApp::test_get_app"], ["tests/test_db.py::TestDb::test_create_db", "tests/test_db.py::TestDb::test_update_db", "tests/test_db.py::TestDb::test_fail_create_db", "tests/test_db.py::TestDb::test_get_dbs", "tests/test_db.py::TestDb::test_get_db", "tests/test_app.py::TestApp::test_update_app_validation", "tests/test_app.py::TestApp::test_enable_force_ssl", "tests/test_app.py::TestApp::test_app_create_validation", "tests/test_app.py::TestApp::test_create_app", "tests/test_app.py::TestApp::test_add_ssl", "tests/test_app.py::TestApp::test_get_app"], ["tests/test_app.py::TestApp::test_create_app", "tests/test_app.py::TestApp::test_get_app"]]}, "tests/test_app.py::TestApp::test_update_app_validation": {"type": "brittle", "detected_sequence": [["tests/test_db.py::TestDb::test_get_dbs", "tests/test_db.py::TestDb::test_create_db", "tests/test_db.py::TestDb::test_get_db", "tests/test_db.py::TestDb::test_fail_create_db", "tests/test_db.py::TestDb::test_update_db", "tests/test_app.py::TestApp::test_create_app", "tests/test_app.py::TestApp::test_add_ssl", "tests/test_app.py::TestApp::test_get_app", "tests/test_app.py::TestApp::test_enable_force_ssl", "tests/test_app.py::TestApp::test_app_create_validation", "tests/test_app.py::TestApp::test_update_app_validation"], ["tests/test_app.py::TestApp::test_add_ssl", "tests/test_app.py::TestApp::test_create_app", "tests/test_app.py::TestApp::test_update_app_validation"], ["tests/test_app.py::TestApp::test_app_create_validation", "tests/test_app.py::TestApp::test_create_app", "tests/test_app.py::TestApp::test_add_ssl", "tests/test_app.py::TestApp::test_update_app_validation"]]}, "tests/test_app.py::TestApp::test_add_ssl": {"type": "brittle", "detected_sequence": [["tests/test_db.py::TestDb::test_create_db", "tests/test_db.py::TestDb::test_get_db", "tests/test_db.py::TestDb::test_get_dbs", "tests/test_db.py::TestDb::test_fail_create_db", "tests/test_db.py::TestDb::test_update_db", "tests/test_app.py::TestApp::test_get_app", "tests/test_app.py::TestApp::test_enable_force_ssl", "tests/test_app.py::TestApp::test_update_app_validation", "tests/test_app.py::TestApp::test_create_app", "tests/test_app.py::TestApp::test_add_ssl"], ["tests/test_db.py::TestDb::test_create_db", "tests/test_db.py::TestDb::test_update_db", "tests/test_db.py::TestDb::test_fail_create_db", "tests/test_db.py::TestDb::test_get_dbs", "tests/test_db.py::TestDb::test_get_db", "tests/test_app.py::TestApp::test_update_app_validation", "tests/test_app.py::TestApp::test_enable_force_ssl", "tests/test_app.py::TestApp::test_app_create_validation", "tests/test_app.py::TestApp::test_create_app", "tests/test_app.py::TestApp::test_add_ssl"], ["tests/test_app.py::TestApp::test_update_app_validation", "tests/test_app.py::TestApp::test_create_app", "tests/test_app.py::TestApp::test_enable_force_ssl", "tests/test_app.py::TestApp::test_app_create_validation", "tests/test_app.py::TestApp::test_get_app", "tests/test_app.py::TestApp::test_add_ssl"]]}, "tests/test_app.py::TestApp::test_enable_force_ssl": {"type": "brittle", "detected_sequence": [["tests/test_db.py::TestDb::test_fail_create_db", "tests/test_db.py::TestDb::test_update_db", "tests/test_db.py::TestDb::test_create_db", "tests/test_db.py::TestDb::test_get_db", "tests/test_db.py::TestDb::test_get_dbs", "tests/test_app.py::TestApp::test_update_app_validation", "tests/test_app.py::TestApp::test_get_app", "tests/test_app.py::TestApp::test_app_create_validation", "tests/test_app.py::TestApp::test_create_app", "tests/test_app.py::TestApp::test_add_ssl", "tests/test_app.py::TestApp::test_enable_force_ssl"], ["tests/test_db.py::TestDb::test_update_db", "tests/test_db.py::TestDb::test_get_db", "tests/test_db.py::TestDb::test_create_db", "tests/test_db.py::TestDb::test_fail_create_db", "tests/test_db.py::TestDb::test_get_dbs", "tests/test_app.py::TestApp::test_get_app", "tests/test_app.py::TestApp::test_create_app", "tests/test_app.py::TestApp::test_update_app_validation", "tests/test_app.py::TestApp::test_add_ssl", "tests/test_app.py::TestApp::test_app_create_validation", "tests/test_app.py::TestApp::test_enable_force_ssl"], ["tests/test_db.py::TestDb::test_get_dbs", "tests/test_db.py::TestDb::test_create_db", "tests/test_db.py::TestDb::test_get_db", "tests/test_db.py::TestDb::test_fail_create_db", "tests/test_db.py::TestDb::test_update_db", "tests/test_app.py::TestApp::test_create_app", "tests/test_app.py::TestApp::test_add_ssl", "tests/test_app.py::TestApp::test_get_app", "tests/test_app.py::TestApp::test_enable_force_ssl"]]}, "tests/test_db.py::TestDb::test_get_db": {"type": "brittle", "detected_sequence": [["tests/test_app.py::TestApp::test_enable_force_ssl", "tests/test_app.py::TestApp::test_update_app_validation", "tests/test_app.py::TestApp::test_app_create_validation", "tests/test_app.py::TestApp::test_get_app", "tests/test_app.py::TestApp::test_create_app", "tests/test_app.py::TestApp::test_add_ssl", "tests/test_db.py::TestDb::test_update_db", "tests/test_db.py::TestDb::test_create_db", "tests/test_db.py::TestDb::test_get_db"], ["tests/test_db.py::TestDb::test_create_db", "tests/test_db.py::TestDb::test_update_db", "tests/test_db.py::TestDb::test_get_dbs", "tests/test_db.py::TestDb::test_get_db"], ["tests/test_db.py::TestDb::test_get_dbs", "tests/test_db.py::TestDb::test_fail_create_db", "tests/test_db.py::TestDb::test_update_db", "tests/test_db.py::TestDb::test_create_db", "tests/test_db.py::TestDb::test_get_db"]]}, "tests/test_db.py::TestDb::test_update_db": {"type": "brittle", "detected_sequence": [["tests/test_db.py::TestDb::test_get_db", "tests/test_db.py::TestDb::test_get_dbs", "tests/test_db.py::TestDb::test_create_db", "tests/test_db.py::TestDb::test_fail_create_db", "tests/test_db.py::TestDb::test_update_db"], ["tests/test_app.py::TestApp::test_get_app", "tests/test_app.py::TestApp::test_update_app_validation", "tests/test_app.py::TestApp::test_enable_force_ssl", "tests/test_app.py::TestApp::test_app_create_validation", "tests/test_app.py::TestApp::test_add_ssl", "tests/test_app.py::TestApp::test_create_app", "tests/test_db.py::TestDb::test_create_db", "tests/test_db.py::TestDb::test_get_dbs", "tests/test_db.py::TestDb::test_get_db", "tests/test_db.py::TestDb::test_update_db"], ["tests/test_db.py::TestDb::test_get_db", "tests/test_db.py::TestDb::test_fail_create_db", "tests/test_db.py::TestDb::test_create_db", "tests/test_db.py::TestDb::test_update_db"]]}, "time": 99.94043278694153}